riyazi/__init__.py
riyazi/setup.py
riyazi/version.py
riyazi/algebra/__init__.py
riyazi/algebra/_basic.py
riyazi/constants/__init__.py
riyazi/constants/codatamath.py
riyazi/constants/codatamath_function.py
riyazi/constants/codataphy.py
riyazi/constants/time.py
riyazi/constants/Strings/mmu.py
riyazi/constants/calculation/Binary_prefixes.py
riyazi/constants/calculation/SI_prefixes.py
riyazi/constants/calculation/__init__.py
riyazi/constants/testing/__init__.py
riyazi/constants/testing/codatamath.py
riyazi/constants/testing/codataphy.py
riyazi/constants/testing/math.py
riyazi/constants/testing/physics.py
riyazi/constants/tests/mm.py
riyazi/constants/tests/time.py
riyazi/core/_a.py
riyazi/core/exponentiation.py
riyazi/core/test.py
riyazi/core/Research/__init__.py
riyazi/core/Research/numbermath.py
riyazi/core/logarithms/__init__.py
riyazi/core/logarithms/_log.py
riyazi/core/logic/__init__.py
riyazi/core/logic/_bitwise.py
riyazi/core/mpmath/Exponential_integrals_and_error_functions.py
riyazi/core/mpmath/Hypergeometric_function.py
riyazi/core/mpmath/power_and_logartihm.py
riyazi/core/numeric/__init__.py
riyazi/core/numeric/basic.py
riyazi/core/series/__init__.py
riyazi/core/series/arithmetic.py
riyazi/core/series/geometric.py
riyazi/core/series/geometric_series.py
riyazi/core/series/harmonic.py
riyazi/core/series/harmonic_series.py
riyazi/core/series/hexagonal_numbers.py
riyazi/core/series/p_series.py
riyazi/core/sets/__init__.py
riyazi/core/sets/set.py
riyazi/core/trigonometry/__init__.py
riyazi/core/trigonometry/_trig.py
riyazi/core/trigonometry/legacy/__init__.py
riyazi/fft/__init__.py
riyazi/fft/_backend.py
riyazi/fft/_basic.py
riyazi/fft/_fftlog.py
riyazi/fft/_fftlog_multimethods.py
riyazi/fft/_helper.py
riyazi/fft/_realtransforms.py
riyazi/fft/setup.py
riyazi/fft/tests/test.py
riyazi/geometry/__init__.py
riyazi/geometry/setup.py
riyazi/geometry/three_dim/__init__.py
riyazi/geometry/three_dim/acute.py
riyazi/geometry/three_dim/cone.py
riyazi-0.17.1.dist-info/LICENSE
riyazi-0.17.1.dist-info/METADATA
riyazi-0.17.1.dist-info/WHEEL
riyazi-0.17.1.dist-info/top_level.txt
riyazi-0.17.1.dist-info/RECORD
