Metadata-Version: 2.1
Name: riyazi
Version: 0.17.1
Summary: riyazi is a mathematics library
Home-page: https:github.com/Mdslauddin/riyazi-main
Author: Md Slauddin
Author-email: mdslauddin285@gmail.com
Maintainer: Md Slauddin
Maintainer-email: mdslauddin285@gmail.com
License: MIT
Keywords: Advance Math,Math,Engineering Math
Classifier: Programming Language :: Python :: 3
Classifier: License :: OSI Approved :: MIT License
Classifier: Operating System :: OS Independent
Requires-Python: >=3.5
License-File: LICENSE
Requires-Dist: numpy
Requires-Dist: scipy
Requires-Dist: mpmath
Requires-Dist: matplotlib
Requires-Dist: msvc-runtime
